<?xml version="1.0" encoding="UTF-8"?>
<plist version="1.0">
<dict>
    <key>name</key>
    <string>Meridian</string>
    <key>settings</key>
    <array>
        <dict>
            <key>scopeName</key>
            <string>source</string>
            <key>settings</key>
            <dict>
                <key>foreground</key>
                <string>#d0d0d0</string>
                <key>background</key>
                <string>#0a0a0a</string>
                <key>caretColor</key>
                <string>#d0d0d0</string>
            </dict>
        </dict>
        <!-- Black -->
        <dict>
            <key>scopeName</key>
            <string>comment</string>
            <key>settings</key>
            <dict>
                <key>foreground</key>
                <string>#1e1e1e</string>
            </dict>
        </dict>
        <!-- Red -->
        <dict>
            <key>scopeName</key>
            <string>keyword</string>
            <key>settings</key>
            <dict>
                <key>foreground</key>
                <string>#9c353e</string>
            </dict>
        </dict>
        <!-- Green -->
        <dict>
            <key>scopeName</key>
            <string>variable</string>
            <key>settings</key>
            <dict>
                <key>foreground</key>
                <string>#7c6f5e</string>
            </dict>
        </dict>
        <!-- Yellow -->
        <dict>
            <key>scopeName</key>
            <string>string</string>
            <key>settings</key>
            <dict>
                <key>foreground</key>
                <string>#d1b57d</string>
            </dict>
        </dict>
        <!-- Blue -->
        <dict>
            <key>scopeName</key>
            <string>constant</string>
            <key>settings</key>
            <dict>
                <key>foreground</key>
                <string>#3a3a3a</string>
            </dict>
        </dict>
        <!-- Magenta -->
        <dict>
            <key>scopeName</key>
            <string>variable.language</string>
            <key>settings</key>
            <dict>
                <key>foreground</key>
                <string>#9c353e</string>
            </dict>
        </dict>
        <!-- Cyan -->
        <dict>
            <key>scopeName</key>
            <string>comment.block</string>
            <key>settings</key>
            <dict>
                <key>foreground</key>
                <string>#5e6b6b</string>
            </dict>
        </dict>
        <!-- White -->
        <dict>
            <key>scopeName</key>
            <string>text</string>
            <key>settings</key>
            <dict>
                <key>foreground</key>
                <string>#d0d0d0</string>
            </dict>
        </dict>
    </array>
</dict>
</plist>
